flask_authorize/__init__.py
flask_authorize/mixins.py
flask_authorize/plugin.py
Flask_Authorize-0.2.7.dist-info/LICENSE
Flask_Authorize-0.2.7.dist-info/METADATA
Flask_Authorize-0.2.7.dist-info/WHEEL
Flask_Authorize-0.2.7.dist-info/top_level.txt
Flask_Authorize-0.2.7.dist-info/RECORD
