Metadata-Version: 2.1
Name: Flask-Authorize
Version: 0.2.7
Summary: Flask plugin for content authorization and access control
Home-page: https://github.com/bprinty/Flask-Authorize
Author: Blake Printy
Author-email: bprinty@gmail.com
License: MIT
Keywords: Flask-Authorize,flask,permissions,authorization,authz,acl,rbac,user,group,role
Platform: any
Classifier: Environment :: Web Environment
Classifier: Intended Audience :: Developers
Classifier: License :: OSI Approved :: MIT License
Classifier: Operating System :: OS Independent
Classifier: Programming Language :: Python
Classifier: Topic :: Internet :: WWW/HTTP :: Dynamic Content
Classifier: Topic :: Software Development :: Libraries :: Python Modules
Classifier: Natural Language :: English
Classifier: Programming Language :: Python :: 3
Classifier: Programming Language :: Python :: 3.3
Classifier: Programming Language :: Python :: 3.4
Classifier: Programming Language :: Python :: 3.5
Classifier: Programming Language :: Python :: 3.6
Classifier: Programming Language :: Python :: 3.7
License-File: LICENSE
Requires-Dist: six
Requires-Dist: Flask
Requires-Dist: SQLAlchemy
Requires-Dist: Flask-SQLAlchemy
